dedupe/__init__.py
dedupe/_init.py
dedupe/api.py
dedupe/backport.py
dedupe/blocking.py
dedupe/canonical.py
dedupe/canopy_index.py
dedupe/clustering.py
dedupe/convenience.py
dedupe/core.py
dedupe/cpredicates.so
dedupe/datamodel.py
dedupe/index.py
dedupe/labeler.py
dedupe/levenshtein.py
dedupe/predicates.py
dedupe/sampling.py
dedupe/serializer.py
dedupe/tfidf.py
dedupe/training.py
dedupe/variables/__init__.py
dedupe/variables/base.py
dedupe/variables/categorical_type.py
dedupe/variables/exact.py
dedupe/variables/exists.py
dedupe/variables/interaction.py
dedupe/variables/latlong.py
dedupe/variables/price.py
dedupe/variables/set.py
dedupe/variables/string.py
dedupe_fh-1.9.7.dist-info/LICENSE
dedupe_fh-1.9.7.dist-info/METADATA
dedupe_fh-1.9.7.dist-info/WHEEL
dedupe_fh-1.9.7.dist-info/top_level.txt
dedupe_fh-1.9.7.dist-info/RECORD
